pyRDDLGym_rl/__init__.py
pyRDDLGym_rl/core/__init__.py
pyRDDLGym_rl/core/agent.py
pyRDDLGym_rl/core/env.py
pyRDDLGym_rl/examples/__init__.py
pyRDDLGym_rl/examples/run_rllib.py
pyRDDLGym_rl/examples/run_stable_baselines.py
pyRDDLGym_rl-0.2.dist-info/LICENSE
pyRDDLGym_rl-0.2.dist-info/METADATA
pyRDDLGym_rl-0.2.dist-info/WHEEL
pyRDDLGym_rl-0.2.dist-info/top_level.txt
pyRDDLGym_rl-0.2.dist-info/RECORD
